kmisc/__init__.py
kmisc-2.1.129.dist-info/LICENSE
kmisc-2.1.129.dist-info/METADATA
kmisc-2.1.129.dist-info/WHEEL
kmisc-2.1.129.dist-info/top_level.txt
kmisc-2.1.129.dist-info/RECORD
