Metadata-Version: 2.1
Name: kmisc
Version: 2.1.129
Summary: Enginering useful library
Home-page: https://github.com/kagepark/kmisc
Author: Kage Park
License: MIT
Platform: UNKNOWN
Classifier: Programming Language :: Python :: 2
Classifier: Programming Language :: Python :: 3
Classifier: License :: OSI Approved :: MIT License
Classifier: Operating System :: OS Independent
License-File: LICENSE
